        {
        "number":"967",
        "name":                                                                                                                                      "Cyclizar",
        "imageUrl":"https://ettet1000.github.io/pokemon_test_new_paldea/paldea/967.png",
        "thumbnailUrl":"https://ettet1000.github.io/pokemon_test_new_paldea/paldea/967_thumb.png",
        "sprites": {
        "mainSpriteUrl":"https://ettet1000.github.io/pokemon_test_new_paldea/paldea/967_main.png"
        },
        "types": [
                 "Dragon",
                 "Normal"
        ],
        "weaknesses":["Fire",
"Psychic",
"Flying",
"Ice"],
"descriptions":["Apparently Cyclizar has been allowing people to ride on its back since ancient times. Depictions of this have been found in 10,000-year-old murals.",
"It can sprint at over 70 mph while carrying a human. The rider's body heat warms Cyclizar's back and lifts the Pokémon's spirit."],
"specie":"Mount",
"height":"63.0 kg (138.9 lbs)",
"weight":"1.6 m (5′03″)",
"breeding":{"egg":{"groups":["Field"],
"cycle":"(7,710–7,966 steps)"},
"genders":[{"type":"MALE",
"percentage":"50%"},
{"type":"FEMALE",
"percentage":"50%"}]},
"training":{"evYield":"2 Speed",
"catchRate":"190 (35.2% with PokéBall, full HP)",
"baseFriendship":"50",
"baseExp":"175",
"growthRate":"Medium Slow"},
"abilities":[{"name":"Shed Skin",
"description":"Powers up Grass-type moves when the Pokémon's HP is low."},{"name":"Regenerator (hidden)",
"description":"Powers up Grass-type moves when the Pokémon's HP is low."}],
"typesEffectiveness":{"Normal":"1",
"Fire":"½",
"Water":"½",
"Electric":"½",
"Grass":"½",
"Ice":"2",
"Fighting":"2",
"Poison":"1",
"Ground":"1",
"Flying":"1",
"Psychic":"1",
"Bug":"1",
"Rock":"1",
"Ghost":"0",
"Dragon":"2",
"Dark":"1",
"Steel":"1",
"Fairy":"2"},
"evolutionChain":[{"number":"967",
"name":"Cyclizar",
"imageUrl":"https://ettet1000.github.io/pokemon_test_new_paldea/paldea/967.png",
"thumbUrl":"https://ettet1000.github.io/pokemon_test_new_paldea/paldea/967_thumb.png",
"type":"FIRST"}],
"previousEvolutions":[],
"nextEvolutions":[],
"superEvolutions":[],
"baseStats":{"hp":70,
"attack":95,
"defense":65,
"spAtk":85,
"spDef":65,
"speed":121,
"total":501},
"cards":
[],
"soundUrl":"https://ettet1000.github.io/pokemon_test_new_paldea/sounds/967.ogg",
"moves":{"levelUp":[{"level":1,
"move":"Tackle",
"type":"Normal",
"category":"Physical",
"power":"40",
"accuracy":"100%"},
{"level":1,
"move":"Growl",
"type":"Normal",
"category":"Status",
"power":"—",
"accuracy":"100%"},
{"level":7,
"move":"Rapid Spin",
"type":"Normal",
"category":"Physical",
"power":"50",
"accuracy":"100%"},
{"level":11,
"move":"Taunt",
"type":"Dark",
"category":"Status",
"power":"—",
"accuracy":"100%"},
{"level":14,
"move":"Breaking Swipe",
"type":"Dragon",
"category":"Physical",
"power":"60",
"accuracy":"100%"},
{"level":18,
"move":"Quick Attack",
"type":"Normal",
"category":"Physical",
"power":"40",
"accuracy":"100%"},
{"level":23,
"move":"Bite",
"type":"Dark",
"category":"Physical",
"power":"60",
"accuracy":"100%"},
{"level":27,
"move":"U-turn",
"type":"Bug",
"category":"Physical",
"power":"70",
"accuracy":"100%"},
{"level":31,
"move":"Shed Tail",
"type":"Normal",
"category":"Status",
"power":"—",
"accuracy":"—%"},
{"level":36,
"move":"Dragon Claw",
"type":"Dragon",
"category":"Physical",
"power":"80",
"accuracy":"100%"},
{"level":40,
"move":"Shift Gear",
"type":"Steel",
"category":"Status",
"power":"—",
"accuracy":"—%"},
{"level":45,
"move":"Dragon Pulse",
"type":"Dragon",
"category":"Special",
"power":"85",
"accuracy":"100%"},
{"level":51,
"move":"Double-Edge",
"type":"Normal",
"category":"Physical",
"power":"120",
"accuracy":"100%"},
{"level":57,
"move":"Dragon Rush",
"type":"Dragon",
"category":"Physical",
"power":"100",
"accuracy":"75%"}],
"technicalMachine":[{"technicalMachine":1,
"move":"Take Down",
"type":"Normal",
"category":"Physical",
"power":"90",
"accuracy":"85%"},
{"technicalMachine":4,
"move":"Agility",
"type":"Psychic",
"category":"Status",
"power":"—",
"accuracy":"—%"},
{"technicalMachine":5,
"move":"Mud-Slap",
"type":"Ground",
"category":"Special",
"power":"20",
"accuracy":"100%"},
{"technicalMachine":7,
"move":"Protect",
"type":"Normal",
"category":"Status",
"power":"—",
"accuracy":"—%"},
{"technicalMachine":8,
"move":"Fire Fang",
"type":"Fire",
"category":"Physical",
"power":"65",
"accuracy":"95%"},
{"technicalMachine":9,
"move":"Thunder Fang",
"type":"Electric",
"category":"Physical",
"power":"65",
"accuracy":"95%"},
{"technicalMachine":14,
"move":"Acrobatics",
"type":"Flying",
"category":"Physical",
"power":"55",
"accuracy":"100%"},
{"technicalMachine":18,
"move":"Thief",
"type":"Dark",
"category":"Physical",
"power":"60",
"accuracy":"100%"},
{"technicalMachine":20,
"move":"Trailblaze",
"type":"Grass",
"category":"Physical",
"power":"50",
"accuracy":"100%"},
{"technicalMachine":25,
"move":"Facade",
"type":"Normal",
"category":"Physical",
"power":"70",
"accuracy":"100%"},
{"technicalMachine":27,
"move":"Aerial Ace",
"type":"Flying",
"category":"Physical",
"power":"60",
"accuracy":"—%"},
{"technicalMachine":35,
"move":"Mud Shot",
"type":"Ground",
"category":"Special",
"power":"55",
"accuracy":"95%"},
{"technicalMachine":44,
"move":"Dragon Tail",
"type":"Dragon",
"category":"Physical",
"power":"60",
"accuracy":"90%"},
{"technicalMachine":47,
"move":"Endure",
"type":"Normal",
"category":"Status",
"power":"—",
"accuracy":"—%"},
{"technicalMachine":49,
"move":"Sunny Day",
"type":"Fire",
"category":"Status",
"power":"—",
"accuracy":"—%"},
{"technicalMachine":50,
"move":"Rain Dance",
"type":"Water",
"category":"Status",
"power":"—",
"accuracy":"—%"},
{"technicalMachine":60,
"move":"U-turn",
"type":"Bug",
"category":"Physical",
"power":"70",
"accuracy":"100%"},
{"technicalMachine":66,
"move":"Body Slam",
"type":"Normal",
"category":"Physical",
"power":"85",
"accuracy":"100%"},
{"technicalMachine":70,
"move":"Sleep Talk",
"type":"Normal",
"category":"Status",
"power":"—",
"accuracy":"—%"},
{"technicalMachine":78,
"move":"Dragon Claw",
"type":"Dragon",
"category":"Physical",
"power":"80",
"accuracy":"100%"},
{"technicalMachine":85,
"move":"Rest",
"type":"Psychic",
"category":"Status",
"power":"—",
"accuracy":"—%"},
{"technicalMachine":87,
"move":"Taunt",
"type":"Dark",
"category":"Status",
"power":"—",
"accuracy":"100%"},
{"technicalMachine":99,
"move":"Iron Head",
"type":"Steel",
"category":"Physical",
"power":"80",
"accuracy":"100%"},
{"technicalMachine":103,
"move":"Substitute",
"type":"Normal",
"category":"Status",
"power":"—",
"accuracy":"—%"},
{"technicalMachine":108,
"move":"Crunch",
"type":"Dark",
"category":"Physical",
"power":"80",
"accuracy":"100%"},
{"technicalMachine":115,
"move":"Dragon Pulse",
"type":"Dragon",
"category":"Special",
"power":"85",
"accuracy":"100%"},
{"technicalMachine":117,
"move":"Hyper Voice",
"type":"Normal",
"category":"Special",
"power":"90",
"accuracy":"100%"},
{"technicalMachine":124,
"move":"Ice Spinner",
"type":"Ice",
"category":"Physical",
"power":"80",
"accuracy":"100%"},
{"technicalMachine":126,
"move":"Thunderbolt",
"type":"Electric",
"category":"Special",
"power":"90",
"accuracy":"100%"},
{"technicalMachine":147,
"move":"Wild Charge",
"type":"Electric",
"category":"Physical",
"power":"90",
"accuracy":"100%"},
{"technicalMachine":152,
"move":"Giga Impact",
"type":"Normal",
"category":"Physical",
"power":"150",
"accuracy":"90%"},
{"technicalMachine":156,
"move":"Outrage",
"type":"Dragon",
"category":"Physical",
"power":"120",
"accuracy":"100%"},
{"technicalMachine":157,
"move":"Overheat",
"type":"Fire",
"category":"Special",
"power":"130",
"accuracy":"90%"},
{"technicalMachine":163,
"move":"Hyper Beam",
"type":"Normal",
"category":"Special",
"power":"150",
"accuracy":"90%"},
{"technicalMachine":169,
"move":"Draco Meteor",
"type":"Dragon",
"category":"Special",
"power":"130",
"accuracy":"90%"},
{"technicalMachine":171,
"move":"Tera Blast",
"type":"Normal",
"category":"Special",
"power":"80",
"accuracy":"100%"}],
"technicalRecords":[],
"egg":[{"move":"Aqua Tail",
"type":"Water",
"category":"Physical",
"power":"90",
"accuracy":"90%"},
{"move":"Iron Tail",
"type":"Steel",
"category":"Physical",
"power":"100",
"accuracy":"75%"},
{"move":"Knock Off",
"type":"Dark",
"category":"Physical",
"power":"65",
"accuracy":"100%"},
{"move":"Power Whip‡",
"type":"Grass",
"category":"Physical",
"power":"120",
"accuracy":"85%"}],
"tutor":[],
"evolution":[],
"preEvolution":[]},
"generation":"GENERATION_I"}
