        {
        "number":"1002",
        "name":                                                                  "파오젠",
        "imageUrl":"https://ettet1000.github.io/pokemon_test_new_paldea/paldea/1002.png",
        "thumbnailUrl":"https://ettet1000.github.io/pokemon_test_new_paldea/paldea/1002_thumb.png",
        "sprites": {
        "mainSpriteUrl":"https://ettet1000.github.io/pokemon_test_new_paldea/paldea/1002_main.png",
        "frontAnimatedSpriteUrl":"https://ettet1000.github.io/pokemon_test_new_paldea/sprites/1002.gif",
        "backAnimatedSpriteUrl":"https://ettet1000.github.io/pokemon_test_new_paldea/sprites/1002.gif",
        "frontShinyAnimatedSpriteUrl":"https://ettet1000.github.io/pokemon_test_new_paldea/sprites/1002.gif",
        "backShinyAnimatedSpriteUrl":"https://ettet1000.github.io/pokemon_test_new_paldea/sprites/1002.gif"
        },
        "types": [
                 "Dark",
                 "Ice"
        ],
        "weaknesses":["Fire",
"Psychic",
"Flying",
"Ice"],
"descriptions":["100t의 눈을 조종한다. 눈사태를 일으키고는 그 안을 드나들며 천진난만하게 논다.",
"먼 옛날, 검에 의해 이슬이 되어 사라진 자들의 증오가 눈을 두르고 포켓몬이 되었다."],
"specie":"재액",
"height":"152.2 kg (335.5 lbs)",
"weight":"1.9 m (6′03″)",
"breeding":{"egg":{"groups":["알미발견"],
"cycle":"(12,850–13,106 걸음)"},
"genders":[{"type":"UNKNOWN"}]},
"training":{"evYield":"3 스피드",
"catchRate":"6 (2.6% 포켓볼과 함께,풀 HP)",
"baseFriendship":"0",
"baseExp":"285",
"growthRate":"느림"},
"abilities":[{"name":"재앙의검",
"description":"Powers up Grass-type moves when the Pokémon's HP is low."}],
"typesEffectiveness":{"Normal":"1",
"Fire":"2",
"Water":"1",
"Electric":"1",
"Grass":"1",
"Ice":"½",
"Fighting":"4",
"Poison":"1",
"Ground":"1",
"Flying":"1",
"Psychic":"0",
"Bug":"2",
"Rock":"2",
"Ghost":"½",
"Dragon":"1",
"Dark":"½",
"Steel":"2",
"Fairy":"2"},
"evolutionChain":[{"number":"1002",
"name":"파오젠",
"imageUrl":"https://ettet1000.github.io/pokemon_test_new_paldea/paldea/1002.png",
"thumbUrl":"https://ettet1000.github.io/pokemon_test_new_paldea/paldea/1002_thumb.png",
"type":"FIRST"}],
"previousEvolutions":[],
"nextEvolutions":[],
"superEvolutions":[],
"baseStats":{"hp":80,
"attack":120,
"defense":80,
"spAtk":90,
"spDef":65,
"speed":135,
"total":570},
"cards":
[],
"soundUrl":"https://ettet1000.github.io/pokemon_test_new_paldea/sounds/1002.ogg",
"moves":{"levelUp":[{"level":1,
"move":"눈싸라기",
"type":"Ice",
"category":"특수",
"power":"40",
"accuracy":"100%"},
{"level":1,
"move":"원한",
"type":"Ghost",
"category":"변화",
"power":"—",
"accuracy":"100%"},
{"level":1,
"move":"검은눈빛",
"type":"Normal",
"category":"변화",
"power":"—",
"accuracy":"—%"},
{"level":5,
"move":"얼다바람",
"type":"Ice",
"category":"특수",
"power":"55",
"accuracy":"95%"},
{"level":10,
"move":"보복",
"type":"Dark",
"category":"물리",
"power":"50",
"accuracy":"100%"},
{"level":15,
"move":"흰안개",
"type":"Ice",
"category":"변화",
"power":"—",
"accuracy":"—%"},
{"level":15,
"move":"흑안개",
"type":"Ice",
"category":"변화",
"power":"—",
"accuracy":"—%"},
{"level":20,
"move":"얼음뭉치",
"type":"Ice",
"category":"물리",
"power":"40",
"accuracy":"100%"},
{"level":25,
"move":"칼춤",
"type":"Normal",
"category":"변화",
"power":"—",
"accuracy":"—%"},
{"level":30,
"move":"설경",
"type":"Ice",
"category":"변화",
"power":"—",
"accuracy":"—%"},
{"level":35,
"move":"깜짝베기",
"type":"Dark",
"category":"물리",
"power":"70",
"accuracy":"100%"},
{"level":40,
"move":"악의파동",
"type":"Dark",
"category":"특수",
"power":"80",
"accuracy":"100%"},
{"level":45,
"move":"고드름떨구기",
"type":"Ice",
"category":"물리",
"power":"85",
"accuracy":"90%"},
{"level":50,
"move":"카타스트로피",
"type":"Dark",
"category":"특수",
"power":"—",
"accuracy":"90%"},
{"level":55,
"move":"기습",
"type":"Dark",
"category":"물리",
"power":"70",
"accuracy":"100%"},
{"level":60,
"move":"성스러운칼",
"type":"Fighting",
"category":"물리",
"power":"90",
"accuracy":"100%"},
{"level":65,
"move":"HP회복",
"type":"Normal",
"category":"변화",
"power":"—",
"accuracy":"—%"},
{"level":70,
"move":"지옥찌르기",
"type":"Dark",
"category":"물리",
"power":"80",
"accuracy":"100%"},
{"level":75,
"move":"절대영도",
"type":"Ice",
"category":"특수",
"power":"—",
"accuracy":"30%"}],
"technicalMachine":[{"technicalMachine":1,
"move":"돌진",
"type":"Normal",
"category":"물리",
"power":"90",
"accuracy":"85%"},
{"technicalMachine":6,
"move":"겁나는얼굴",
"type":"Normal",
"category":"변화",
"power":"—",
"accuracy":"100%"},
{"technicalMachine":7,
"move":"방어",
"type":"Normal",
"category":"변화",
"power":"—",
"accuracy":"—%"},
{"technicalMachine":10,
"move":"얼음엄니",
"type":"Ice",
"category":"물리",
"power":"65",
"accuracy":"95%"},
{"technicalMachine":14,
"move":"애크러뱃",
"type":"Flying",
"category":"물리",
"power":"55",
"accuracy":"100%"},
{"technicalMachine":25,
"move":"객기",
"type":"Normal",
"category":"물리",
"power":"70",
"accuracy":"100%"},
{"technicalMachine":27,
"move":"제비반환",
"type":"Flying",
"category":"물리",
"power":"60",
"accuracy":"—%"},
{"technicalMachine":29,
"move":"병상첨병",
"type":"Ghost",
"category":"특수",
"power":"65",
"accuracy":"100%"},
{"technicalMachine":30,
"move":"바크아웃",
"type":"Dark",
"category":"특수",
"power":"55",
"accuracy":"95%"},
{"technicalMachine":34,
"move":"얼다바람",
"type":"Ice",
"category":"특수",
"power":"55",
"accuracy":"95%"},
{"technicalMachine":46,
"move":"눈사태",
"type":"Ice",
"category":"물리",
"power":"60",
"accuracy":"100%"},
{"technicalMachine":47,
"move":"버티기",
"type":"Normal",
"category":"변화",
"power":"—",
"accuracy":"—%"},
{"technicalMachine":50,
"move":"비바라기",
"type":"Water",
"category":"변화",
"power":"—",
"accuracy":"—%"},
{"technicalMachine":52,
"move":"설경",
"type":"Ice",
"category":"변화",
"power":"—",
"accuracy":"—%"},
{"technicalMachine":57,
"move":"칼등치기",
"type":"Normal",
"category":"물리",
"power":"40",
"accuracy":"100%"},
{"technicalMachine":58,
"move":"깨트리다",
"type":"Fighting",
"category":"물리",
"power":"75",
"accuracy":"100%"},
{"technicalMachine":63,
"move":"사이코팽",
"type":"Psychic",
"category":"물리",
"power":"85",
"accuracy":"100%"},
{"technicalMachine":70,
"move":"잠꼬대",
"type":"Normal",
"category":"변화",
"power":"—",
"accuracy":"—%"},
{"technicalMachine":85,
"move":"잠자기",
"type":"Psychic",
"category":"변화",
"power":"—",
"accuracy":"—%"},
{"technicalMachine":87,
"move":"도발",
"type":"Dark",
"category":"변화",
"power":"—",
"accuracy":"100%"},
{"technicalMachine":88,
"move":"칼춤",
"type":"Normal",
"category":"변화",
"power":"—",
"accuracy":"—%"},
{"technicalMachine":94,
"move":"악의파동",
"type":"Dark",
"category":"특수",
"power":"80",
"accuracy":"100%"},
{"technicalMachine":103,
"move":"대타출동",
"type":"Normal",
"category":"변화",
"power":"—",
"accuracy":"—%"},
{"technicalMachine":108,
"move":"깨물어부수기",
"type":"Dark",
"category":"물리",
"power":"80",
"accuracy":"100%"},
{"technicalMachine":124,
"move":"아이스스피너",
"type":"Ice",
"category":"물리",
"power":"80",
"accuracy":"100%"},
{"technicalMachine":143,
"move":"눈보라",
"type":"Ice",
"category":"특수",
"power":"110",
"accuracy":"70%"},
{"technicalMachine":152,
"move":"기가임팩트",
"type":"Normal",
"category":"물리",
"power":"150",
"accuracy":"90%"},
{"technicalMachine":163,
"move":"파괴광선",
"type":"Normal",
"category":"특수",
"power":"150",
"accuracy":"90%"},
{"technicalMachine":171,
"move":"테라버스트",
"type":"Normal",
"category":"특수",
"power":"80",
"accuracy":"100%"}],
"technicalRecords":[],
"egg":[],
"tutor":[],
"evolution":[],
"preEvolution":[]},
"generation":"GENERATION_I"}
